mamba2_triton_guard/__init__.py
mamba2_triton_guard/cli.py
mamba2_triton_guard/patcher.py
mamba2_triton_guard-0.1.0.dist-info/METADATA
mamba2_triton_guard-0.1.0.dist-info/WHEEL
mamba2_triton_guard-0.1.0.dist-info/entry_points.txt
mamba2_triton_guard-0.1.0.dist-info/top_level.txt
mamba2_triton_guard-0.1.0.dist-info/RECORD
