Metadata-Version: 2.4
Name: mamba2-triton-guard
Version: 0.1.0
Summary: Patch mamba2_torch on Apple Silicon to bypass Triton imports.
Author: Cosmo
License: MIT
Requires-Python: >=3.9
